framer/__init__.py
framer/main.py
ua_framer-0.0.1.dist-info/LICENSE
ua_framer-0.0.1.dist-info/METADATA
ua_framer-0.0.1.dist-info/WHEEL
ua_framer-0.0.1.dist-info/top_level.txt
ua_framer-0.0.1.dist-info/RECORD
