Metadata-Version: 2.1
Name: ua-framer
Version: 0.0.1
Summary: Draw the frame of the Ukrainian flag on the image.
Home-page: https://github.com/Nemu627/UA-framer
Author: Nemu627
Author-email: nemu.otoyume@gmail.com
License: UNKNOWN
Platform: UNKNOWN
Classifier: Programming Language :: Python :: 3.7
Classifier: License :: OSI Approved :: MIT License
Classifier: Operating System :: OS Independent
License-File: LICENSE
